{
  "46394": {
    "nft_id": 46394,
    "pool": "?/?",
    "in_range": true,
    "is_active": 0,
    "ownership_status": null,
    "owner_address": null,
    "last_check": "2025-11-07 01:07:20"
  },
  "49059": {
    "nft_id": 49059,
    "pool": "?/?",
    "in_range": true,
    "is_active": 0,
    "ownership_status": null,
    "owner_address": null,
    "last_check": "2025-11-07 01:07:21"
  },
  "49062": {
    "nft_id": 49062,
    "pool": "?/?",
    "in_range": true,
    "is_active": 0,
    "ownership_status": null,
    "owner_address": null,
    "last_check": "2025-11-07 01:07:22"
  },
  "49127": {
    "nft_id": 49127,
    "pool": "?/?",
    "in_range": true,
    "is_active": 0,
    "ownership_status": null,
    "owner_address": null,
    "last_check": "2025-11-07 01:07:23"
  },
  "49135": {
    "nft_id": 49135,
    "pool": "?/?",
    "in_range": true,
    "is_active": 0,
    "ownership_status": null,
    "owner_address": null,
    "last_check": "2025-11-07 01:07:24"
  },
  "49211": {
    "nft_id": 49211,
    "pool": "?/?",
    "in_range": true,
    "is_active": 0,
    "ownership_status": null,
    "owner_address": null,
    "last_check": "2025-11-07 01:07:25"
  },
  "49275": {
    "nft_id": 49275,
    "pool": "?/?",
    "in_range": true,
    "is_active": 0,
    "ownership_status": null,
    "owner_address": null,
    "last_check": "2025-11-07 01:07:27"
  },
  "49276": {
    "nft_id": 49276,
    "pool": "?/?",
    "in_range": true,
    "is_active": 0,
    "ownership_status": null,
    "owner_address": null,
    "last_check": "2025-11-07 01:07:28"
  },
  "49342": {
    "nft_id": 49342,
    "pool": "?/?",
    "in_range": true,
    "is_active": 0,
    "ownership_status": null,
    "owner_address": null,
    "last_check": "2025-11-07 01:07:29"
  },
  "49501": {
    "nft_id": 49501,
    "pool": "?/?",
    "in_range": true,
    "is_active": 0,
    "ownership_status": null,
    "owner_address": null,
    "last_check": "2025-11-07 01:07:30"
  },
  "49511": {
    "nft_id": 49511,
    "pool": "?/?",
    "in_range": true,
    "is_active": 0,
    "ownership_status": null,
    "owner_address": null,
    "last_check": "2025-11-07 01:07:31"
  },
  "49512": {
    "nft_id": 49512,
    "pool": "?/?",
    "in_range": true,
    "is_active": 0,
    "ownership_status": null,
    "owner_address": null,
    "last_check": "2025-11-07 01:07:32"
  },
  "49515": {
    "nft_id": 49515,
    "pool": "?/?",
    "in_range": true,
    "is_active": 0,
    "ownership_status": null,
    "owner_address": null,
    "last_check": "2025-11-07 01:07:33"
  },
  "49532": {
    "nft_id": 49532,
    "pool": "?/?",
    "in_range": true,
    "is_active": 0,
    "ownership_status": null,
    "owner_address": null,
    "last_check": "2025-11-07 01:07:34"
  },
  "49619": {
    "nft_id": 49619,
    "pool": "?/?",
    "in_range": true,
    "is_active": 0,
    "ownership_status": null,
    "owner_address": null,
    "last_check": "2025-11-07 01:07:35"
  },
  "49620": {
    "nft_id": 49620,
    "pool": "?/?",
    "in_range": true,
    "is_active": 0,
    "ownership_status": null,
    "owner_address": null,
    "last_check": "2025-11-07 01:07:36"
  },
  "49623": {
    "nft_id": 49623,
    "pool": "?/?",
    "in_range": true,
    "is_active": 0,
    "ownership_status": null,
    "owner_address": null,
    "last_check": "2025-11-07 01:07:38"
  },
  "49634": {
    "nft_id": 49634,
    "pool": "?/?",
    "in_range": true,
    "is_active": 0,
    "ownership_status": null,
    "owner_address": null,
    "last_check": "2025-11-07 01:07:39"
  },
  "49635": {
    "nft_id": 49635,
    "pool": "?/?",
    "in_range": true,
    "is_active": 0,
    "ownership_status": null,
    "owner_address": null,
    "last_check": "2025-11-07 01:07:40"
  },
  "49651": {
    "nft_id": 49651,
    "pool": "?/?",
    "in_range": true,
    "is_active": 0,
    "ownership_status": null,
    "owner_address": null,
    "last_check": "2025-11-07 01:07:41"
  },
  "49655": {
    "nft_id": 49655,
    "pool": "?/?",
    "in_range": true,
    "is_active": 0,
    "ownership_status": null,
    "owner_address": null,
    "last_check": "2025-11-07 01:07:42"
  },
  "49659": {
    "nft_id": 49659,
    "pool": "?/?",
    "in_range": true,
    "is_active": 0,
    "ownership_status": null,
    "owner_address": null,
    "last_check": "2025-11-07 01:07:43"
  },
  "49660": {
    "nft_id": 49660,
    "pool": "?/?",
    "in_range": true,
    "is_active": 0,
    "ownership_status": null,
    "owner_address": null,
    "last_check": "2025-11-07 01:07:44"
  },
  "49767": {
    "nft_id": 49767,
    "pool": "?/?",
    "in_range": true,
    "is_active": 0,
    "ownership_status": null,
    "owner_address": null,
    "last_check": "2025-11-07 01:07:45"
  },
  "49768": {
    "nft_id": 49768,
    "pool": "?/?",
    "in_range": true,
    "is_active": 0,
    "ownership_status": null,
    "owner_address": null,
    "last_check": "2025-11-07 01:07:46"
  },
  "49805": {
    "nft_id": 49805,
    "pool": "?/?",
    "in_range": true,
    "is_active": 0,
    "ownership_status": null,
    "owner_address": null,
    "last_check": "2025-11-07 01:07:48"
  },
  "49928": {
    "nft_id": 49928,
    "pool": "?/?",
    "in_range": true,
    "is_active": 0,
    "ownership_status": null,
    "owner_address": null,
    "last_check": "2025-11-07 01:07:49"
  },
  "49929": {
    "nft_id": 49929,
    "pool": "?/?",
    "in_range": true,
    "is_active": 0,
    "ownership_status": null,
    "owner_address": null,
    "last_check": "2025-11-07 01:07:50"
  },
  "49934": {
    "nft_id": 49934,
    "pool": "?/?",
    "in_range": true,
    "is_active": 0,
    "ownership_status": null,
    "owner_address": null,
    "last_check": "2025-11-07 01:07:51"
  },
  "49935": {
    "nft_id": 49935,
    "pool": "?/?",
    "in_range": true,
    "is_active": 0,
    "ownership_status": null,
    "owner_address": null,
    "last_check": "2025-11-07 01:07:52"
  },
  "50050": {
    "nft_id": 50050,
    "pool": "?/?",
    "in_range": true,
    "is_active": 0,
    "ownership_status": null,
    "owner_address": null,
    "last_check": "2025-11-07 01:07:53"
  },
  "50051": {
    "nft_id": 50051,
    "pool": "?/?",
    "in_range": true,
    "is_active": 0,
    "ownership_status": null,
    "owner_address": null,
    "last_check": "2025-11-07 01:07:54"
  },
  "50052": {
    "nft_id": 50052,
    "pool": "?/?",
    "in_range": true,
    "is_active": 0,
    "ownership_status": null,
    "owner_address": null,
    "last_check": "2025-11-07 01:07:55"
  },
  "50055": {
    "nft_id": 50055,
    "pool": "?/?",
    "in_range": true,
    "is_active": 0,
    "ownership_status": null,
    "owner_address": null,
    "last_check": "2025-11-07 01:07:56"
  },
  "50058": {
    "nft_id": 50058,
    "pool": "?/?",
    "in_range": true,
    "is_active": 0,
    "ownership_status": null,
    "owner_address": null,
    "last_check": "2025-11-07 01:07:57"
  },
  "50059": {
    "nft_id": 50059,
    "pool": "?/?",
    "in_range": true,
    "is_active": 0,
    "ownership_status": null,
    "owner_address": null,
    "last_check": "2025-11-07 01:07:59"
  },
  "50060": {
    "nft_id": 50060,
    "pool": "?/?",
    "in_range": true,
    "is_active": 0,
    "ownership_status": null,
    "owner_address": null,
    "last_check": "2025-11-07 01:08:00"
  },
  "50157": {
    "nft_id": 50157,
    "pool": "FXRP/USD₮0",
    "in_range": false,
    "is_active": true,
    "ownership_status": null,
    "owner_address": null,
    "last_check": "2025-11-07 01:08:06"
  },
  "50158": {
    "nft_id": 50158,
    "pool": "WFLR/USD₮0",
    "in_range": false,
    "is_active": true,
    "ownership_status": null,
    "owner_address": null,
    "last_check": "2025-11-07 01:08:11"
  }
}